checkon/__init__.py
checkon/__main__.py
checkon/app.py
checkon/cli.py
checkon/results.py
checkon/satests.py
checkon/scripts/checkon_trial/__init__.py
checkon/scripts/checkon_trial/checkon_trial/checkon_trial.py
checkon/scripts/checkon_trial/setup.py
checkon/tests.py
checkon/tox.py
checkon-0.1.4.dist-info/entry_points.txt
checkon-0.1.4.dist-info/LICENSE
checkon-0.1.4.dist-info/WHEEL
checkon-0.1.4.dist-info/METADATA
checkon-0.1.4.dist-info/RECORD
