Metadata-Version: 2.1
Name: checkon
Version: 0.1.4
Summary: Support backward compatibility by running your users' test suites.
License: GPL-3.0
Author: Checkon contributors
Author-email: checkon@cordaz.com
Requires-Python: >=3.7,<4.0
Classifier: License :: OSI Approved :: GNU General Public License v3 (GPLv3)
Classifier: Programming Language :: Python :: 3
Classifier: Programming Language :: Python :: 3.7
Provides-Extra: docs
Requires-Dist: attrs (==19.1.0)
Requires-Dist: click (==7.0)
Requires-Dist: hyperlink (>=19.0,<20.0)
Requires-Dist: inflection (>=0.3.1,<0.4.0)
Requires-Dist: junitparser (>=1.3,<2.0)
Requires-Dist: marshmallow (>=3.0,<4.0)
Requires-Dist: marshmallow-dataclass (==6.0.0rc5)
Requires-Dist: pendulum (>=2.0,<3.0)
Requires-Dist: pyrsistent (>=0.14.11,<0.15.0)
Requires-Dist: requests (>=2.22,<3.0)
Requires-Dist: requirements-parser (>=0.2.0,<0.3.0)
Requires-Dist: sqlalchemy (>=1.3,<2.0)
Requires-Dist: tabulate (>=0.8.3,<0.9.0)
Requires-Dist: toml (>=0.10.0,<0.11.0)
Requires-Dist: tox-run-command (>=0.4.0,<0.5.0)
Requires-Dist: xmltodict (>=0.12.0,<0.13.0)
